nsopy/__init__.py
nsopy/loggers.py
nsopy/methods_factory.py
nsopy/observer_pattern.py
nsopy/template_methods.py
nsopy/utils.py
nsopy/methods/__init__.py
nsopy/methods/base.py
nsopy/methods/bundle.py
nsopy/methods/quasi_monotone.py
nsopy/methods/subgradient.py
nsopy/methods/universal.py
nsopy-1.52.dist-info/METADATA
nsopy-1.52.dist-info/RECORD
nsopy-1.52.dist-info/WHEEL
nsopy-1.52.dist-info/top_level.txt
tests/__init__.py
tests/analytical_oracles.py
tests/test_bundle_methods.py
tests/test_quasi_monotone_subgradient_methods.py
tests/test_subgradient_methods.py
tests/test_universal_gradient_methods.py
tests/test_utils.py
